Optimal_Partition_Search.py
Optimal_Partition_Search-0.0.1.dist-info/LICENSE
Optimal_Partition_Search-0.0.1.dist-info/METADATA
Optimal_Partition_Search-0.0.1.dist-info/WHEEL
Optimal_Partition_Search-0.0.1.dist-info/top_level.txt
Optimal_Partition_Search-0.0.1.dist-info/RECORD
