Metadata-Version: 2.1
Name: Optimal-Partition-Search
Version: 0.0.1
Summary: A function used to find the number of partitions required to speed up the array searching process
Home-page: https://github.com/fork123aniket/Optimal-Partition-Search
Author: Aniket Saxena
License: UNKNOWN
Keywords: optimal search,array search,optimal partition search,searching algorithms
Platform: UNKNOWN
Classifier: Programming Language :: Python :: 3
Classifier: License :: OSI Approved :: MIT License
Classifier: Operating System :: OS Independent
Requires-Python: >=3.9
